version/__init__.py
version/_version.py
whathappened/__init__.py
whathappened/changelog.py
whathappened/changelog_all.py
whathappened/command_line.py
whathappened/git_commits.py
whathappened-1.1.0.dist-info/LICENSE
whathappened-1.1.0.dist-info/METADATA
whathappened-1.1.0.dist-info/WHEEL
whathappened-1.1.0.dist-info/entry_points.txt
whathappened-1.1.0.dist-info/top_level.txt
whathappened-1.1.0.dist-info/RECORD
